workshop_sergioo/__init__.py
workshop_sergioo/main.py
workshop_sergioo-0.1.0.dist-info/license
workshop_sergioo-0.1.0.dist-info/METADATA
workshop_sergioo-0.1.0.dist-info/WHEEL
workshop_sergioo-0.1.0.dist-info/RECORD
