Metadata-Version: 2.1
Name: workshop-sergioo
Version: 0.1.0
Summary: 
Author: RafaelRodrigues
Author-email: rafael.rodrigues85@hotmail.com
Requires-Python: >=3.12,<4.0
Classifier: Programming Language :: Python :: 3
Classifier: Programming Language :: Python :: 3.12
